<?xml version="1.0" encoding="UTF-8"?>
<tour apprev="17253" start="node1" appversion="6.0.2">
  <panorama hideabout="1" id="node1">
    <input leveltileurl="tiles/node1/cf_%c/l_%l/c_%x/tile_%y.jpg" levelbiashidpi="1.000" levelingpitch="0" width="1750" height="1750" overlap="1" leveltilesize="510" levelbias="0.400" levelingroll="0">
      <level preload="0" width="1750" height="1750" predecode="0"/>
      <level preload="0" width="875" height="875" predecode="0"/>
      <level preload="1" width="437" height="437" predecode="1"/>
      <preview color="0x808080" strip="1"/>
    </input>
    <view pannorth="0" fovmode="0">
      <start tilt="0" pan="-90" projection="4" fov="70"/>
      <flyin tilt="-90" pan="0" projection="9" fov="170"/>
      <min tilt="-90" fovpixel="2" pan="-360"/>
      <max scaletofit="1" tilt="90" fovstereographic="270" pan="0" fov="120" fovfisheye="360"/>
    </view>
    <userdata description="" latitude="" tags="050_11.01.2019|1_Floor" source="" author="" longitude="" datetime="" info="" copyright="" customnodeid="" title="" comment="">
      <mapcoords y="-2.331" y_floorplan_percent="82.81374900079936" mapid="FloorPlan01" x_floorplan_percent="50.8" x="1.42875"/>
    </userdata>
    <hotspots wordwrap="1" width="180" height="20">
      <label backgroundcolor="0xffffff" border="1" wordwrap="1" backgroundalpha="1" enabled="0" width="180" borderradius="1" borderalpha="1" textalpha="1" textcolor="0x000000" height="20" bordercolor="0x000000" background="1"/>
      <polystyle backgroundcolor="0xffffff" mode="0" backgroundalpha="0.2509803921568627" handcursor="1" borderalpha="1" bordercolor="0x595959"/>
      <polyhotspot description="" target="" url="{node7}" id="Poly02" title="">
        <polystring>-342.28/-44.67|-11.43/-45.76|-11.77/27.7|-342.86/26.48</polystring>
      </polyhotspot>
      <polyhotspot description="" target="" url="{node9}" id="Poly01" title="">
        <polystring>-44.45/-38.76|-73.05/-48.16|-73.2/29.23|-44.07/21.71</polystring>
      </polyhotspot>
      <polyhotspot description="" target="" url="{node10}" id="Poly04" title="">
        <polystring>-150.79/-60.36|-91.81/-54.03|-92.33/33.54|-149.98/40.44</polystring>
      </polyhotspot>
    </hotspots>
    <media/>
    <transition zoomfov="20" type="crossdissolve" blendcolor="0x000000" zoomspeed="2" enabled="1" softedge="0" blendtime="1" zoomin="0" zoomout="0" zoomoutpause="1"/>
    <animation animsequence="Animation01" syncanimationwithvideo="0" useinautorotation="0"/>
    <control hideabout="1" simulatemass="1" rubberband="0" lockedmouse="0" sensitivity="8" invertwheel="0" contextfullscreen="1" speedwheel="1" lockedkeyboardzoom="0" lockedkeyboard="0" dblclickfullscreen="0" contextprojections="1" lockedwheel="0" invertcontrol="1"/>
  </panorama>
  <panorama hideabout="1" id="node7">
    <input leveltileurl="tiles/node7/cf_%c/l_%l/c_%x/tile_%y.jpg" levelbiashidpi="1.000" levelingpitch="0" width="1750" height="1750" overlap="1" leveltilesize="510" levelbias="0.400" levelingroll="0">
      <level preload="0" width="1750" height="1750" predecode="0"/>
      <level preload="0" width="875" height="875" predecode="0"/>
      <level preload="1" width="437" height="437" predecode="1"/>
      <preview color="0x808080" strip="1"/>
    </input>
    <view pannorth="0" fovmode="0">
      <start tilt="0" pan="0" projection="4" fov="70"/>
      <flyin tilt="-90" pan="0" projection="9" fov="170"/>
      <min tilt="-90" fovpixel="2" pan="0"/>
      <max scaletofit="1" tilt="90" fovstereographic="270" pan="360" fov="120" fovfisheye="360"/>
    </view>
    <userdata description="" latitude="" tags="PANO|1_Floor" source="" author="" longitude="" datetime="" info="" copyright="" customnodeid="" title="" comment="">
      <mapcoords y="-2.286" y_floorplan_percent="81.21502797761791" mapid="FloorPlan01" x_floorplan_percent="27.6" x="0.77625"/>
    </userdata>
    <hotspots wordwrap="1" width="180" height="20">
      <label backgroundcolor="0xffffff" border="1" wordwrap="1" backgroundalpha="1" enabled="0" width="180" borderradius="1" borderalpha="1" textalpha="1" textcolor="0x000000" height="20" bordercolor="0x000000" background="1"/>
      <polystyle backgroundcolor="0xffffff" mode="0" backgroundalpha="0.2509803921568627" handcursor="1" borderalpha="1" bordercolor="0x595959"/>
      <polyhotspot description="" target="" url="{node1}" id="Poly01" title="">
        <polystring>-223.47/46.73|-155.61/52.52|-155.47/-68.23|-224.23/-64.39</polystring>
      </polyhotspot>
    </hotspots>
    <media/>
    <transition zoomfov="20" type="crossdissolve" blendcolor="0x000000" zoomspeed="2" enabled="1" softedge="0" blendtime="1" zoomin="0" zoomout="0" zoomoutpause="1"/>
    <animation animsequence="Animation01" syncanimationwithvideo="0" useinautorotation="0"/>
    <control hideabout="1" simulatemass="1" rubberband="0" lockedmouse="0" sensitivity="8" invertwheel="0" contextfullscreen="1" speedwheel="1" lockedkeyboardzoom="0" lockedkeyboard="0" dblclickfullscreen="0" contextprojections="1" lockedwheel="0" invertcontrol="1"/>
  </panorama>
  <panorama hideabout="1" id="node8">
    <input leveltileurl="tiles/node8/cf_%c/l_%l/c_%x/tile_%y.jpg" levelbiashidpi="1.000" levelingpitch="0" width="1750" height="1750" overlap="1" leveltilesize="510" levelbias="0.400" levelingroll="0">
      <level preload="0" width="1750" height="1750" predecode="0"/>
      <level preload="0" width="875" height="875" predecode="0"/>
      <level preload="1" width="437" height="437" predecode="1"/>
      <preview color="0x808080" strip="1"/>
    </input>
    <view pannorth="0" fovmode="0">
      <start tilt="0" pan="-50" projection="4" fov="70"/>
      <flyin tilt="-90" pan="0" projection="9" fov="170"/>
      <min tilt="-90" fovpixel="2" pan="-360"/>
      <max scaletofit="1" tilt="90" fovstereographic="270" pan="0" fov="120" fovfisheye="360"/>
    </view>
    <userdata description="" latitude="" tags="PANO|1_Floor" source="" author="" longitude="" datetime="" info="" copyright="" customnodeid="" title="" comment="">
      <mapcoords y="-2.3175" y_floorplan_percent="82.33413269384492" mapid="FloorPlan01" x_floorplan_percent="71.59999999999999" x="2.01375"/>
    </userdata>
    <hotspots wordwrap="1" width="180" height="20">
      <label backgroundcolor="0xffffff" border="1" wordwrap="1" backgroundalpha="1" enabled="0" width="180" borderradius="1" borderalpha="1" textalpha="1" textcolor="0x000000" height="20" bordercolor="0x000000" background="1"/>
      <polystyle backgroundcolor="0xffffff" mode="0" backgroundalpha="0.2509803921568627" handcursor="1" borderalpha="1" bordercolor="0x595959"/>
      <polyhotspot description="" target="" url="{node10}" id="Poly02" title="">
        <polystring>-29.45/-73.01|-148.39/-74.93|-149.46/62.25|-27.5/59.27</polystring>
      </polyhotspot>
    </hotspots>
    <media/>
    <transition zoomfov="20" type="crossdissolve" blendcolor="0x000000" zoomspeed="2" enabled="1" softedge="0" blendtime="1" zoomin="0" zoomout="0" zoomoutpause="1"/>
    <animation animsequence="Animation01" syncanimationwithvideo="0" useinautorotation="0"/>
    <control hideabout="1" simulatemass="1" rubberband="0" lockedmouse="0" sensitivity="8" invertwheel="0" contextfullscreen="1" speedwheel="1" lockedkeyboardzoom="0" lockedkeyboard="0" dblclickfullscreen="0" contextprojections="1" lockedwheel="0" invertcontrol="1"/>
  </panorama>
  <panorama hideabout="1" id="node9">
    <input leveltileurl="tiles/node9/cf_%c/l_%l/c_%x/tile_%y.jpg" levelbiashidpi="1.000" levelingpitch="0" width="1750" height="1750" overlap="1" leveltilesize="510" levelbias="0.400" levelingroll="0">
      <level preload="0" width="1750" height="1750" predecode="0"/>
      <level preload="0" width="875" height="875" predecode="0"/>
      <level preload="1" width="437" height="437" predecode="1"/>
      <preview color="0x808080" strip="1"/>
    </input>
    <view pannorth="0" fovmode="0">
      <start tilt="0" pan="-90" projection="4" fov="70"/>
      <flyin tilt="-90" pan="0" projection="9" fov="170"/>
      <min tilt="-90" fovpixel="2" pan="-360"/>
      <max scaletofit="1" tilt="90" fovstereographic="270" pan="0" fov="120" fovfisheye="360"/>
    </view>
    <userdata description="" latitude="" tags="PANO|1_Floor" source="" author="" longitude="" datetime="" info="" copyright="" customnodeid="" title="" comment="">
      <mapcoords y="-1.45125" y_floorplan_percent="51.55875299760192" mapid="FloorPlan01" x_floorplan_percent="29.2" x="0.8212499999999999"/>
    </userdata>
    <hotspots wordwrap="1" width="180" height="20">
      <label backgroundcolor="0xffffff" border="1" wordwrap="1" backgroundalpha="1" enabled="0" width="180" borderradius="1" borderalpha="1" textalpha="1" textcolor="0x000000" height="20" bordercolor="0x000000" background="1"/>
      <polystyle backgroundcolor="0xffffff" mode="0" backgroundalpha="0.2509803921568627" handcursor="1" borderalpha="1" bordercolor="0x595959"/>
      <polyhotspot description="" target="" url="{node1}" id="Poly04" title="">
        <polystring>-220.42/-36.22|-220.04/20.44|-229.71/24.02|-230.22/-40.8</polystring>
      </polyhotspot>
      <polyhotspot description="" target="" url="{node11}" id="Poly01" title="">
        <polystring>-126.33/-25.58|-137.06/-22.53|-136.64/23.85|-125.61/18.88</polystring>
      </polyhotspot>
      <polyhotspot description="" target="" url="{node13}" id="Poly02" title="">
        <polystring>-74.64/-28.75|-93.97/-30.33|-92.07/24.57|-74.6/23.26</polystring>
      </polyhotspot>
    </hotspots>
    <media/>
    <transition zoomfov="20" type="crossdissolve" blendcolor="0x000000" zoomspeed="2" enabled="1" softedge="0" blendtime="1" zoomin="0" zoomout="0" zoomoutpause="1"/>
    <animation animsequence="Animation01" syncanimationwithvideo="0" useinautorotation="0"/>
    <control hideabout="1" simulatemass="1" rubberband="0" lockedmouse="0" sensitivity="8" invertwheel="0" contextfullscreen="1" speedwheel="1" lockedkeyboardzoom="0" lockedkeyboard="0" dblclickfullscreen="0" contextprojections="1" lockedwheel="0" invertcontrol="1"/>
  </panorama>
  <panorama hideabout="1" id="node10">
    <input leveltileurl="tiles/node10/cf_%c/l_%l/c_%x/tile_%y.jpg" levelbiashidpi="1.000" levelingpitch="0" width="1750" height="1750" overlap="1" leveltilesize="510" levelbias="0.400" levelingroll="0">
      <level preload="0" width="1750" height="1750" predecode="0"/>
      <level preload="0" width="875" height="875" predecode="0"/>
      <level preload="1" width="437" height="437" predecode="1"/>
      <preview color="0x808080" strip="1"/>
    </input>
    <view pannorth="0" fovmode="0">
      <start tilt="0" pan="-90" projection="4" fov="70"/>
      <flyin tilt="-90" pan="0" projection="9" fov="170"/>
      <min tilt="-90" fovpixel="2" pan="-360"/>
      <max scaletofit="1" tilt="90" fovstereographic="270" pan="0" fov="120" fovfisheye="360"/>
    </view>
    <userdata description="" latitude="" tags="PANO|1_Floor" source="" author="" longitude="" datetime="" info="" copyright="" customnodeid="" title="" comment="">
      <mapcoords y="-1.94625" y_floorplan_percent="69.14468425259793" mapid="FloorPlan01" x_floorplan_percent="64.40000000000001" x="1.81125"/>
    </userdata>
    <hotspots wordwrap="1" width="180" height="20">
      <label backgroundcolor="0xffffff" border="1" wordwrap="1" backgroundalpha="1" enabled="0" width="180" borderradius="1" borderalpha="1" textalpha="1" textcolor="0x000000" height="20" bordercolor="0x000000" background="1"/>
      <polystyle backgroundcolor="0xffffff" mode="0" backgroundalpha="0.2509803921568627" handcursor="1" borderalpha="1" bordercolor="0x595959"/>
      <polyhotspot description="" target="" url="{node12}" id="Poly01" title="">
        <polystring>-173.56/-53.38|-219.48/-47.59|-217.84/37.31|-187.59/43.93|-173.68/25.49|-173.97/0.05</polystring>
      </polyhotspot>
      <polyhotspot description="" target="" url="{node11}" id="Poly02" title="">
        <polystring>-57.63/-44.84|-145.37/-38.13|-138.09/0.75|-114.15/26.78|-59.11/21.72</polystring>
      </polyhotspot>
      <polyhotspot description="" target="" url="{node8}" id="Poly03" title="">
        <polystring>-227.84/-47.59|-260.69/-56.12|-260.48/37.06|-227.44/29.27</polystring>
      </polyhotspot>
      <polyhotspot description="" target="" url="{node1}" id="Poly04" title="">
        <polystring>-290.58/-63.76|-359.17/-56.83|-358.95/37.29|-290.86/45.1</polystring>
      </polyhotspot>
    </hotspots>
    <media/>
    <transition zoomfov="20" type="crossdissolve" blendcolor="0x000000" zoomspeed="2" enabled="1" softedge="0" blendtime="1" zoomin="0" zoomout="0" zoomoutpause="1"/>
    <animation animsequence="Animation01" syncanimationwithvideo="0" useinautorotation="0"/>
    <control hideabout="1" simulatemass="1" rubberband="0" lockedmouse="0" sensitivity="8" invertwheel="0" contextfullscreen="1" speedwheel="1" lockedkeyboardzoom="0" lockedkeyboard="0" dblclickfullscreen="0" contextprojections="1" lockedwheel="0" invertcontrol="1"/>
  </panorama>
  <panorama hideabout="1" id="node11">
    <input leveltileurl="tiles/node11/cf_%c/l_%l/c_%x/tile_%y.jpg" levelbiashidpi="1.000" levelingpitch="0" width="1750" height="1750" overlap="1" leveltilesize="510" levelbias="0.400" levelingroll="0">
      <level preload="0" width="1750" height="1750" predecode="0"/>
      <level preload="0" width="875" height="875" predecode="0"/>
      <level preload="1" width="437" height="437" predecode="1"/>
      <preview color="0x808080" strip="1"/>
    </input>
    <view pannorth="0" fovmode="0">
      <start tilt="0" pan="0" projection="4" fov="70"/>
      <flyin tilt="-90" pan="0" projection="9" fov="170"/>
      <min tilt="-90" fovpixel="2" pan="0"/>
      <max scaletofit="1" tilt="90" fovstereographic="270" pan="360" fov="120" fovfisheye="360"/>
    </view>
    <userdata description="" latitude="" tags="PANO|1_Floor" source="" author="" longitude="" datetime="" info="" copyright="" customnodeid="" title="" comment="">
      <mapcoords y="-1.035" y_floorplan_percent="36.77058353317346" mapid="FloorPlan01" x_floorplan_percent="73.59999999999999" x="2.07"/>
    </userdata>
    <hotspots wordwrap="1" width="180" height="20">
      <label backgroundcolor="0xffffff" border="1" wordwrap="1" backgroundalpha="1" enabled="0" width="180" borderradius="1" borderalpha="1" textalpha="1" textcolor="0x000000" height="20" bordercolor="0x000000" background="1"/>
      <polystyle backgroundcolor="0xffffff" mode="0" backgroundalpha="0.2509803921568627" handcursor="1" borderalpha="1" bordercolor="0x595959"/>
      <polyhotspot description="" target="" url="{node10}" id="Poly01" title="">
        <polystring>-273/-40.5|-272.25/-8.11|-279.37/10.72|-291.38/19.18|-316.9/17.11|-317.15/-31.13</polystring>
      </polyhotspot>
      <polyhotspot description="" target="" url="{node9}" id="Poly02" title="">
        <polystring>-4.93/-35.75|-27.14/-33.12|-25.87/22.58|-4.72/24.73</polystring>
      </polyhotspot>
      <polyhotspot description="" target="" url="{node12}" id="Poly03" title="">
        <polystring>-247.75/25.94|-307.66/23.63|-308.19/35.58|-319.76/42.18|-243.63/51.12</polystring>
      </polyhotspot>
    </hotspots>
    <media/>
    <transition zoomfov="20" type="crossdissolve" blendcolor="0x000000" zoomspeed="2" enabled="1" softedge="0" blendtime="1" zoomin="0" zoomout="0" zoomoutpause="1"/>
    <animation animsequence="Animation01" syncanimationwithvideo="0" useinautorotation="0"/>
    <control hideabout="1" simulatemass="1" rubberband="0" lockedmouse="0" sensitivity="8" invertwheel="0" contextfullscreen="1" speedwheel="1" lockedkeyboardzoom="0" lockedkeyboard="0" dblclickfullscreen="0" contextprojections="1" lockedwheel="0" invertcontrol="1"/>
  </panorama>
  <panorama hideabout="1" id="node12">
    <input leveltileurl="tiles/node12/cf_%c/l_%l/c_%x/tile_%y.jpg" levelbiashidpi="1.000" levelingpitch="0" width="1750" height="1750" overlap="1" leveltilesize="510" levelbias="0.400" levelingroll="0">
      <level preload="0" width="1750" height="1750" predecode="0"/>
      <level preload="0" width="875" height="875" predecode="0"/>
      <level preload="1" width="437" height="437" predecode="1"/>
      <preview color="0x808080" strip="1"/>
    </input>
    <view pannorth="0" fovmode="0">
      <start tilt="0" pan="-90" projection="4" fov="70"/>
      <flyin tilt="-90" pan="0" projection="9" fov="170"/>
      <min tilt="-90" fovpixel="2" pan="-360"/>
      <max scaletofit="1" tilt="90" fovstereographic="270" pan="0" fov="120" fovfisheye="360"/>
    </view>
    <userdata description="" latitude="" tags="PANO|2_Floor" source="" author="" longitude="" datetime="" info="" copyright="" customnodeid="" title="" comment="">
      <mapcoords y="-2.025" y_floorplan_percent="71.94244604316546" mapid="FloorPlan02" x_floorplan_percent="60" x="1.6875"/>
    </userdata>
    <hotspots wordwrap="1" width="180" height="20">
      <label backgroundcolor="0xffffff" border="1" wordwrap="1" backgroundalpha="1" enabled="0" width="180" borderradius="1" borderalpha="1" textalpha="1" textcolor="0x000000" height="20" bordercolor="0x000000" background="1"/>
      <polystyle backgroundcolor="0xffffff" mode="0" backgroundalpha="0.2509803921568627" handcursor="1" borderalpha="1" bordercolor="0x595959"/>
      <polyhotspot description="" target="" url="{node10}" id="Poly01" title="">
        <polystring>-67.5/-41.79|-86.43/-10.31|-125.24/-8.27|-164.59/-15.82|-152.85/-25.86|-152.91/-47.13|-128.95/-60.93|-129.1/-38.81</polystring>
      </polyhotspot>
    </hotspots>
    <media/>
    <transition zoomfov="20" type="crossdissolve" blendcolor="0x000000" zoomspeed="2" enabled="1" softedge="0" blendtime="1" zoomin="0" zoomout="0" zoomoutpause="1"/>
    <animation animsequence="Animation01" syncanimationwithvideo="0" useinautorotation="0"/>
    <control hideabout="1" simulatemass="1" rubberband="0" lockedmouse="0" sensitivity="8" invertwheel="0" contextfullscreen="1" speedwheel="1" lockedkeyboardzoom="0" lockedkeyboard="0" dblclickfullscreen="0" contextprojections="1" lockedwheel="0" invertcontrol="1"/>
  </panorama>
  <panorama hideabout="1" id="node13">
    <input leveltileurl="tiles/node13/cf_%c/l_%l/c_%x/tile_%y.jpg" levelbiashidpi="1.000" levelingpitch="0" width="1750" height="1750" overlap="1" leveltilesize="510" levelbias="0.400" levelingroll="0">
      <level preload="0" width="1750" height="1750" predecode="0"/>
      <level preload="0" width="875" height="875" predecode="0"/>
      <level preload="1" width="437" height="437" predecode="1"/>
      <preview color="0x808080" strip="1"/>
    </input>
    <view pannorth="0" fovmode="0">
      <start tilt="0" pan="90" projection="4" fov="70"/>
      <flyin tilt="-90" pan="0" projection="9" fov="170"/>
      <min tilt="-90" fovpixel="2" pan="0"/>
      <max scaletofit="1" tilt="90" fovstereographic="270" pan="360" fov="120" fovfisheye="360"/>
    </view>
    <userdata description="" latitude="" tags="PANO4|1_Floor" source="" author="" longitude="" datetime="" info="" copyright="" customnodeid="" title="" comment="">
      <mapcoords y="-0.4275" y_floorplan_percent="15.18784972022382" mapid="FloorPlan01" x_floorplan_percent="27.6" x="0.77625"/>
    </userdata>
    <hotspots wordwrap="1" width="180" height="20">
      <label backgroundcolor="0xffffff" border="1" wordwrap="1" backgroundalpha="1" enabled="0" width="180" borderradius="1" borderalpha="1" textalpha="1" textcolor="0x000000" height="20" bordercolor="0x000000" background="1"/>
      <polystyle backgroundcolor="0xffffff" mode="0" backgroundalpha="0.2509803921568627" handcursor="1" borderalpha="1" bordercolor="0x595959"/>
      <polyhotspot description="" target="" url="{node9}" id="Poly01" title="">
        <polystring>-264.72/-57.59|-309.84/-51.72|-310.07/42.66|-267.26/49.67</polystring>
      </polyhotspot>
    </hotspots>
    <media/>
    <transition zoomfov="20" type="crossdissolve" blendcolor="0x000000" zoomspeed="2" enabled="1" softedge="0" blendtime="1" zoomin="0" zoomout="0" zoomoutpause="1"/>
    <animation animsequence="Animation01" syncanimationwithvideo="0" useinautorotation="0"/>
    <control hideabout="1" simulatemass="1" rubberband="0" lockedmouse="0" sensitivity="8" invertwheel="0" contextfullscreen="1" speedwheel="1" lockedkeyboardzoom="0" lockedkeyboard="0" dblclickfullscreen="0" contextprojections="1" lockedwheel="0" invertcontrol="1"/>
  </panorama>
  <masternode>
    <userdata description="" latitude="" tags="" source="" author="" longitude="" datetime="" info="" copyright="" customnodeid="" title="" comment=""/>
  </masternode>
  <map zoomlevels="4" floorplannorth="267.34" type="file" transparent="0" width="2500" tileformat="png" id="FloorPlan01" bgcolor="rgba(255, 255, 255, 1)" height="2502" title="1_Floor"/>
  <map zoomlevels="4" floorplannorth="274.33" type="file" transparent="0" width="2500" tileformat="png" id="FloorPlan02" bgcolor="rgba(255, 255, 255, 1)" height="2502" title="2_Floor"/>
</tour>
